mengling_tool2/__init__.py
mengling_tool2/desktop.ini
mengling_tool2/genetic_algorithm.py
mengling_tool2/play.py
mengling_tool2/__pycache__/__init__.cpython-39.pyc
mengling_tool2/advanced_process/api.py
mengling_tool2/advanced_process/dataflow.py
mengling_tool2/advanced_process/key_value.py
mengling_tool2/advanced_process/thread_task.py
mengling_tool2/advanced_process/__pycache__/thread_task.cpython-39.pyc
mengling_tool2/advanced_process/combine_data2/config.py
mengling_tool2/advanced_process/combine_data2/data.py
mengling_tool2/advanced_process/combine_data2/insert.py
mengling_tool2/advanced_process/combine_data2/main.py
mengling_tool2/advanced_process/combine_data2/模板.py
mengling_tool2/advanced_process/combine_data2/__pycache__/config.cpython-39.pyc
mengling_tool2/advanced_process/combine_data2/__pycache__/data.cpython-39.pyc
mengling_tool2/advanced_process/combine_data2/__pycache__/insert.cpython-39.pyc
mengling_tool2/advanced_process/combine_data2/__pycache__/main.cpython-39.pyc
mengling_tool2/advanced_tools/gp_tool.py
mengling_tool2/advanced_tools/radar.py
mengling_tool2/advanced_tools/redis_schedule.py
mengling_tool2/advanced_tools/schedule.py
mengling_tool2/advanced_tools/week_schedule.py
mengling_tool2/advanced_tools/__pycache__/gp_tool.cpython-39.pyc
mengling_tool2/advanced_tools/__redis_schedule__/run.py
mengling_tool2/advanced_tools/__redis_schedule__/save_task.py
mengling_tool2/advanced_tools/__redis_schedule__/base/__body__.py
mengling_tool2/advanced_tools/__redis_schedule__/base/body.py
mengling_tool2/advanced_tools/__redis_schedule__/mold/arg.py
mengling_tool2/advanced_tools/__redis_schedule__/mold/status.py
mengling_tool2/data/analysis.py
mengling_tool2/data/make.py
mengling_tool2/data/structure.py
mengling_tool2/data/__pycache__/make.cpython-39.pyc
mengling_tool2/data/__pycache__/structure.cpython-39.pyc
mengling_tool2/data/__structure__/dynamic_cache.py
mengling_tool2/data/__structure__/goods.py
mengling_tool2/data/__structure__/link.py
mengling_tool2-1.5.1.dist-info/METADATA
mengling_tool2-1.5.1.dist-info/WHEEL
mengling_tool2-1.5.1.dist-info/top_level.txt
mengling_tool2-1.5.1.dist-info/RECORD
